MontyCarlo/__init__.py
MontyCarlo/_init.cp38-win_amd64.pyd
MontyCarlo/plotter.py
MontyCarlo/settings.py
MontyCarlo/setup.py
MontyCarlo/sources.cp38-win_amd64.pyd
MontyCarlo/types.cp38-win_amd64.pyd
MontyCarlo/_random/__init__.py
MontyCarlo/_random/interface.cp38-win_amd64.pyd
MontyCarlo/geometry/CSG.cp38-win_amd64.pyd
MontyCarlo/geometry/__init__.py
MontyCarlo/geometry/graph.py
MontyCarlo/geometry/main.cp38-win_amd64.pyd
MontyCarlo/geometry/sdf/__init__.py
MontyCarlo/geometry/sdf/d2.py
MontyCarlo/geometry/sdf/d3.py
MontyCarlo/geometry/sdf/dn.py
MontyCarlo/geometry/sdf/ease.py
MontyCarlo/geometry/sdf/mesh.py
MontyCarlo/geometry/sdf/progress.py
MontyCarlo/geometry/sdf/stl.py
MontyCarlo/geometry/sdf/text.py
MontyCarlo/geometry/sdf/util.py
MontyCarlo/materials/__init__.py
MontyCarlo/materials/database.py
MontyCarlo/materials/elements.py
MontyCarlo/materials/logger.py
MontyCarlo/materials/materials.cp38-win_amd64.pyd
MontyCarlo/materials/pyRelax.cp38-win_amd64.pyd
MontyCarlo/materials/setup.py
MontyCarlo/materials/electron/BREM.cp38-win_amd64.pyd
MontyCarlo/materials/electron/GOS.cp38-win_amd64.pyd
MontyCarlo/materials/electron/GOSfinal.cp38-win_amd64.pyd
MontyCarlo/materials/electron/GOSmake_softIMFP.cp38-win_amd64.pyd
MontyCarlo/materials/electron/__init__.py
MontyCarlo/materials/electron/main.cp38-win_amd64.pyd
MontyCarlo/materials/electron/makeBrem.py
MontyCarlo/materials/electron/makeElastic2.py
MontyCarlo/materials/electron/makeGOS.py
MontyCarlo/materials/electron/temp.py
MontyCarlo/materials/photon/CrossSection.cp38-win_amd64.pyd
MontyCarlo/materials/photon/__init__.py
MontyCarlo/materials/photon/photon.cp38-win_amd64.pyd
MontyCarlo/materials/photon/photon1.cp38-win_amd64.pyd
MontyCarlo/materials/photon/photon111.py
MontyCarlo/materials/photon/coherent/FormFactor.py
MontyCarlo/materials/photon/coherent/FormFactorAnalysis.py
MontyCarlo/materials/photon/coherent/FormFactorWriter.py
MontyCarlo/materials/photon/coherent/__init__.py
Generic_model_class-0.0.3.dist-info/LICENSE
Generic_model_class-0.0.3.dist-info/METADATA
Generic_model_class-0.0.3.dist-info/WHEEL
Generic_model_class-0.0.3.dist-info/top_level.txt
Generic_model_class-0.0.3.dist-info/RECORD
