Metadata-Version: 2.1
Name: Generic-model-class
Version: 0.0.3
Summary: A fast general purpose Monte Carlo simulation of radiation transport.
Home-page: https://github.com/RuiFilipeCampos/MontyCarlo
Author: Rui Filipe de Sousa Campos
Author-email: ruifilipedesousacampos@gmail.com
License: UNKNOWN
Project-URL: Bug Tracker, https://github.com/RuiFilipeCampos/MontyCarlo/issues
Platform: UNKNOWN
Classifier: Programming Language :: Python :: 3
Classifier: Operating System :: OS Independent
Requires-Python: >=3.6
